xia_engine_gitlab_project/__init__.py
xia_engine_gitlab_project/engine.cpython-310-darwin.so
xia_engine_gitlab_project/engine_issue.cpython-310-darwin.so
xia_engine_gitlab_project/engine_milestone.cpython-310-darwin.so
xia_engine_gitlab_project/engine_notes.cpython-310-darwin.so
xia_engine_gitlab_project-0.0.7.dist-info/LICENSE.txt
xia_engine_gitlab_project-0.0.7.dist-info/METADATA
xia_engine_gitlab_project-0.0.7.dist-info/WHEEL
xia_engine_gitlab_project-0.0.7.dist-info/top_level.txt
xia_engine_gitlab_project-0.0.7.dist-info/RECORD
