Metadata-Version: 2.1
Name: xia-engine-gitlab-project
Version: 0.0.7
Summary: UNKNOWN
Home-page: https://develop.x-i-a.com/docs/xia-engine-gitlab-project/0.0.7/index.html
Author: X-I-A
Author-email: admin@x-i-a.com
License: UNKNOWN
Platform: UNKNOWN
Requires-Python: >=3.9
License-File: LICENSE.txt
Requires-Dist: requests
Requires-Dist: PyYAML
Requires-Dist: xia-engine-gitlab
